[
  {
    "monto": 21,
    "tipo": "100",
    "cf": 100,
    "sf": 0,
    "iva": 21
  },
  {
    "monto": 18.90,
    "tipo": "90-10",
    "cf": 90,
    "sf": 10,
    "iva": 21
  },
  {
    "monto": 16.8,
    "tipo": "80-20",
    "cf": 80,
    "sf": 20,
    "iva": 21
  },
  {
    "monto": 14.7,
    "tipo": "70-30",
    "cf": 70,
    "sf": 30,
    "iva": 21
  },
  {
    "monto": 12.6,
    "tipo": "60-40",
    "cf": 60,
    "sf": 40,
    "iva": 21
  },
  {
    "monto": 10.5,
    "tipo": "50-50",
    "cf": 50,
    "sf": 50,
    "iva": 21
  },
  {
    "monto": 0,
    "tipo": "0",
    "cf": 0,
    "sf": 100,
    "iva": 21
  }
]